MANIFEST.in
README.rst
requirements.txt
setup.py
tox.ini
doc/conf.py
doc/index.rst
doc/intro.rst
doc/tutorial.rst
doc/.hypothesis/eval_source/hypothesis_temporary_module_0338617ff66788f1ab9d5142f849106ae9b38d15.py
doc/.hypothesis/eval_source/hypothesis_temporary_module_0529b12987b897d7290f83bcbcc804e28602383d.py
doc/.hypothesis/eval_source/hypothesis_temporary_module_080187190c9678ad026ff7798702777438a6c116.py
doc/.hypothesis/eval_source/hypothesis_temporary_module_122a8f9fcdccd59b90df58d0558e44bcca216ab8.py
doc/.hypothesis/eval_source/hypothesis_temporary_module_12562534fc1cd5ce9e48ce9f6025a94d4071d7a1.py
doc/.hypothesis/eval_source/hypothesis_temporary_module_12c1d00d532807965223eb08a44fcda50c228e44.py
doc/.hypothesis/eval_source/hypothesis_temporary_module_157a06c7111ab0b1f1a33822a57773ed79d45d30.py
doc/.hypothesis/eval_source/hypothesis_temporary_module_157c02e78a2f3560de74aceff294a8477134e84e.py
doc/.hypothesis/eval_source/hypothesis_temporary_module_18a332bae68cd42ec9a38dc0ba292cfef80615b6.py
doc/.hypothesis/eval_source/hypothesis_temporary_module_1eba03841185292c6018ae372c9f399bb5b99054.py
doc/.hypothesis/eval_source/hypothesis_temporary_module_27293c5549237bae7b26a5803947ff8c4f839122.py
doc/.hypothesis/eval_source/hypothesis_temporary_module_2cea1af442c7f053fe19b734be9a6a80bbafb877.py
doc/.hypothesis/eval_source/hypothesis_temporary_module_2dea9c7498284093108163b15d385b516d6fb6c5.py
doc/.hypothesis/eval_source/hypothesis_temporary_module_2e71923a5f523fc7899142bce080a648f473d503.py
doc/.hypothesis/eval_source/hypothesis_temporary_module_302a2bf2b98d37c182da92de76c16ff408d9447c.py
doc/.hypothesis/eval_source/hypothesis_temporary_module_319ade46afdab08a61611170bc661bd6b6fd0507.py
doc/.hypothesis/eval_source/hypothesis_temporary_module_31b625635c53e0532b2ea931ab0f3f201dd6cbc8.py
doc/.hypothesis/eval_source/hypothesis_temporary_module_3c94c71e9e33e081b43be6e2046f3a3f8fab3067.py
src/bytesize.egg-info/PKG-INFO
src/bytesize.egg-info/SOURCES.txt
src/bytesize.egg-info/dependency_links.txt
src/bytesize.egg-info/top_level.txt
